aogl/__init__.py
aogl/__main__.py
aogl/aogl.py
aogl-0.1.dist-info/LICENCE
aogl-0.1.dist-info/METADATA
aogl-0.1.dist-info/WHEEL
aogl-0.1.dist-info/entry_points.txt
aogl-0.1.dist-info/top_level.txt
aogl-0.1.dist-info/RECORD
